sswrap/__init__.py
sswrap/exceptions.py
sswrap/spreadsheet.py
sswrap/worksheet.py
sswrap/writable_spreadsheet.py
sswrap/writable_worksheet.py
tests/__init__.py
tests/test_empty.py
tests/test_sswrap.py
sswrap-0.0.1.dist-info/LICENSE
sswrap-0.0.1.dist-info/METADATA
sswrap-0.0.1.dist-info/WHEEL
sswrap-0.0.1.dist-info/entry_points.txt
sswrap-0.0.1.dist-info/top_level.txt
sswrap-0.0.1.dist-info/RECORD
