Metadata-Version: 2.1
Name: sswrap
Version: 0.0.1
Summary: Spreadsheet and Worksheet wrapper
Home-page: https://github.com/dmiyakawa/sswrap
Author: Daisuke Miyakawa
Author-email: 2149473+dmiyakawa@users.noreply.github.com
Maintainer: Daisuke Miyakawa
Maintainer-email: 2149473+dmiyakawa@users.noreply.github.com
License: Apache 2
Platform: UNKNOWN
Classifier: Development Status :: 3 - Alpha
Classifier: Programming Language :: Python :: 3
Classifier: Programming Language :: Python :: 3.6
Classifier: Programming Language :: Python :: 3.7
Classifier: Programming Language :: Python :: 3.8
Classifier: Topic :: Software Development :: Libraries
Classifier: License :: OSI Approved :: Apache Software License
License-File: LICENSE
